statchat/__init__.py
statchat-0.0.0.dist-info/METADATA
statchat-0.0.0.dist-info/WHEEL
statchat-0.0.0.dist-info/top_level.txt
statchat-0.0.0.dist-info/RECORD
